LICENSE
MANIFEST.in
README.rst
VERSION
requirements.txt
setup.py
unicore/__init__.py
unicore/__init__.pyc
unicore.hub.client.egg-info/PKG-INFO
unicore.hub.client.egg-info/SOURCES.txt
unicore.hub.client.egg-info/dependency_links.txt
unicore.hub.client.egg-info/namespace_packages.txt
unicore.hub.client.egg-info/not-zip-safe
unicore.hub.client.egg-info/requires.txt
unicore.hub.client.egg-info/top_level.txt
unicore/hub/__init__.py
unicore/hub/__init__.pyc
unicore/hub/client/__init__.py
unicore/hub/client/__init__.pyc
unicore/hub/client/appclient.py
unicore/hub/client/appclient.pyc
unicore/hub/client/base.py
unicore/hub/client/base.pyc
unicore/hub/client/userclient.py
unicore/hub/client/userclient.pyc
unicore/hub/client/utils.py
unicore/hub/client/utils.pyc
unicore/hub/client/tests/__init__.py
unicore/hub/client/tests/__init__.pyc
unicore/hub/client/tests/test_app.py
unicore/hub/client/tests/test_client.py
unicore/hub/client/tests/test_user.py
unicore/hub/client/tests/__pycache__/test_app.cpython-27-PYTEST.pyc
unicore/hub/client/tests/__pycache__/test_client.cpython-27-PYTEST.pyc
unicore/hub/client/tests/__pycache__/test_user.cpython-27-PYTEST.pyc